{"_id":{"$oid":"6109dc9adcf23a013990701d"},"available_times":["11:00am - 12:00pm","12:00pm - 1:00pm","6:00pm - 7:00pm","7:00pm - 8:00pm","8:00pm - 9:00pm"],"restaurant_name":"Happy Burgers","restaurant_location":"Betoota, QLD","restaurant_image":"images/burger.jpg","capacity":35,"__v":0}
{"_id":{"$oid":"6109e1dd9eeb470171aa29f6"},"available_times":["11:00am - 12:00pm","12:00pm - 1:00pm","6:00pm - 7:00pm","7:00pm - 8:00pm","8:00pm - 9:00pm"],"restaurant_name":"Zoli's Pasta","restaurant_location":"Betoota, QLD","restaurant_image":"images/pasta.jpg","capacity":60,"__v":0}
{"_id":{"$oid":"6109e2099eeb470171aa29f8"},"available_times":["11:00am - 12:00pm","12:00pm - 1:00pm","6:00pm - 7:00pm","7:00pm - 8:00pm","8:00pm - 9:00pm"],"restaurant_name":"Bombay Sensation","restaurant_location":"Betoota, QLD","restaurant_image":"images/indian.jpg","capacity":45,"__v":0}
{"_id":{"$oid":"6109e25a9eeb470171aa29fa"},"available_times":["6:00pm - 7:00pm","7:00pm - 8:00pm","8:00pm - 9:00pm"],"restaurant_name":"Sunset Japanese","restaurant_location":"Betoota, QLD","restaurant_image":"images/japanese.jpg","capacity":20,"__v":0}
{"_id":{"$oid":"6109e29d9eeb470171aa29fc"},"available_times":["6:00pm - 7:00pm","7:00pm - 8:00pm","8:00pm - 9:00pm","9:00pm - 10:00pm"],"restaurant_name":"YummyCha","restaurant_location":"Betoota, QLD","restaurant_image":"images/yumcha.jpg","capacity":25,"__v":0}
{"_id":{"$oid":"6109e3039eeb470171aa29fe"},"available_times":["10:00am - 11:00am","11:00am - 12:00pm","12:00pm - 1:00pm","1:00pm - 2:00pm"],"restaurant_name":"Sushi Bus","restaurant_location":"Betoota, QLD","restaurant_image":"images/sushi.jpg","capacity":35,"__v":0}
